Metadata-Version: 2.1
Name: Wifi-Checker
Version: 0.0.2
Summary: A easy wifi checker // Un semplice verificatore di connesione
Home-page: UNKNOWN
Author: IlProgrammatore.py
Author-email: asciart2008@gmail.com
License: MIT
Keywords: Wifi_Checker
Platform: UNKNOWN
Classifier: Development Status :: 5 - Production/Stable
Classifier: Intended Audience :: Education
Classifier: Operating System :: Microsoft :: Windows :: Windows 10
Classifier: License :: OSI Approved :: MIT License
Classifier: Programming Language :: Python :: 3
License-File: LICENSE.txt
